{
	"list":[{
		"id":"1",
		"link":"productlist.html",
		"src":"http://pic.metromall.cn/Resource/AdFlashPic/1901170942230.jpg"
	},{
		"id":"2",
		"link":"productlist.html",
		"src":"http://pic.metromall.cn/Resource/AdFlashPic/1901171603070.jpg"
	},{
		"id":"3",
		"link":"productlist.html",
		"src":"http://pic.metromall.cn/Resource/AdFlashPic/1901111313103.jpg"
	},{
		"id":"4",
		"link":"productlist.html",
		"src":"http://pic.metromall.cn/Resource/AdFlashPic/1812311425543.jpg"
	},{
		"id":"5",
		"link":"productlist.html",
		"src":"http://pic.metromall.cn/Resource/AdFlashPic/1901171603070.jpg"
	},{
		"id":"6",
		"link":"productlist.html",
		"src":"http://pic.metromall.cn/Resource/AdFlashPic/1901111312121.jpg"
	}]
	

}